{
  "cragdynasubscribe": {
    "subtitle": "subtitles.cragdynasubscribe",
    "sounds": [
      {
        "name": "youtubers_natural_disasters:on-my-way-_112",
        "stream": false
      }
    ]
  },
  "cragdynadeath": {
    "subtitle": "subtitles.cragdynadeath",
    "sounds": [
      {
        "name": "youtubers_natural_disasters:new_recording_2",
        "stream": false
      }
    ]
  },
  "cavemanfilmswhateveryouwant": {
    "subtitle": "subtitles.cavemanfilmswhateveryouwant",
    "sounds": [
      {
        "name": "youtubers_natural_disasters:cavemanfilmscoolaudio",
        "stream": false
      }
    ]
  },
  "defnotarickrollatall": {
    "subtitle": "subtitles.defnotarickrollatall",
    "sounds": [
      {
        "name": "youtubers_natural_disasters:defnotrickroll",
        "stream": false
      }
    ]
  },
  "thatswhatiliketommy": {
    "subtitle": "subtitles.thatswhatiliketommy",
    "sounds": [
      {
        "name": "youtubers_natural_disasters:thatswhatiliketommy",
        "stream": false
      }
    ]
  },
  "technobladeneverdies": {
    "subtitle": "subtitles.technobladeneverdies",
    "sounds": [
      {
        "name": "youtubers_natural_disasters:technoblade-never-dies",
        "stream": false
      }
    ]
  }
}